tomegathericon/utils/logFormatter/__init__.py
tomegathericon/utils/logFormatter/classes/__init__.py
tomegathericon/utils/logFormatter/classes/formatter_config.py
tomegathericon/utils/logFormatter/classes/formatter_type.py
tomegathericon/utils/logFormatter/classes/log_formatter.py
tomegathericon/utils/logFormatter/classes/py.typed
tomegathericon/utils/logFormatter/py.typed
tomegathericon_utils_log_formatter-0.0.3.dist-info/METADATA
tomegathericon_utils_log_formatter-0.0.3.dist-info/WHEEL
tomegathericon_utils_log_formatter-0.0.3.dist-info/RECORD
