Metadata-Version: 2.3
Name: tomegathericon-utils-log-formatter
Version: 0.0.3
Summary: Formatter to be used with tomegatherion-utils-logger
License: Software License Agreement
Author: Abhishek Kapoor
Author-email: kapoor.abhishek@outlook.com
Requires-Python: >=3.12,<4.0
Classifier: License :: Other/Proprietary License
Classifier: Programming Language :: Python :: 3
Classifier: Programming Language :: Python :: 3.12
Classifier: Programming Language :: Python :: 3.13
Requires-Dist: poetry-core (>=2.1.3,<3.0.0)
Requires-Dist: tomegathericon-utils-exceptions (>=0.0.2,<0.0.3)
